{
  "static": {
    "action_add": "https://cdn.discordapp.com/emojis/1442619108058202213.png",
    "action_check": "https://cdn.discordapp.com/emojis/1442619110138843258.png",
    "action_info": "https://cdn.discordapp.com/emojis/1442619111283626005.png",
    "action_question": "https://cdn.discordapp.com/emojis/1442619112349237421.png",
    "action_remove": "https://cdn.discordapp.com/emojis/1442619113385234547.png",
    "action_warning": "https://cdn.discordapp.com/emojis/1442619114664362035.png",
    "action_x": "https://cdn.discordapp.com/emojis/1442619115779920025.png",
    "arrow_down": "https://cdn.discordapp.com/emojis/1442619119164719194.png",
    "arrow_downleft": "https://cdn.discordapp.com/emojis/1442619120515285143.png",
    "arrow_downright": "https://cdn.discordapp.com/emojis/1442619121756934207.png",
    "arrow_left": "https://cdn.discordapp.com/emojis/1442619123346444299.png",
    "arrow_right": "https://cdn.discordapp.com/emojis/1442619124751536259.png",
    "arrow_up": "https://cdn.discordapp.com/emojis/1442619126567796757.png",
    "arrow_upleft": "https://cdn.discordapp.com/emojis/1442619127742074910.png",
    "arrow_upright": "https://cdn.discordapp.com/emojis/1442619130556715142.png",
    "bell_add": "https://cdn.discordapp.com/emojis/1442619132838281226.png",
    "bell_check": "https://cdn.discordapp.com/emojis/1442619133874409504.png",
    "bell_off": "https://cdn.discordapp.com/emojis/1442619134985900216.png",
    "bell_remove": "https://cdn.discordapp.com/emojis/1442619136583798906.png",
    "bell_x": "https://cdn.discordapp.com/emojis/1442619137858732092.png",
    "bell": "https://cdn.discordapp.com/emojis/1442619138865631365.png",
    "apps_chrome": "https://cdn.discordapp.com/emojis/1442619140681498706.png",
    "apps_discord": "https://cdn.discordapp.com/emojis/1442619141902041218.png",
    "apps_figma": "https://cdn.discordapp.com/emojis/1442619145459073064.png",
    "apps_github": "https://cdn.discordapp.com/emojis/1442619146339876926.png",
    "apps_instagram": "https://cdn.discordapp.com/emojis/1442619147879190569.png",
    "apps_pinterest": "https://cdn.discordapp.com/emojis/1442619149099733145.png",
    "apps_spotify": "https://cdn.discordapp.com/emojis/1442619150391443521.png",
    "apps_twitch": "https://cdn.discordapp.com/emojis/1442619151721173152.png",
    "apps_vscode": "https://cdn.discordapp.com/emojis/1442619152882991274.png",
    "apps_x": "https://cdn.discordapp.com/emojis/1442619154858508381.png",
    "apps_youtube": "https://cdn.discordapp.com/emojis/1442619156028588113.png",
    "calendar_add": "https://cdn.discordapp.com/emojis/1442619157160919253.png",
    "calendar_check": "https://cdn.discordapp.com/emojis/1442619158264152094.png",
    "calendar_remove": "https://cdn.discordapp.com/emojis/1442619159497408612.png",
    "calendar_x": "https://cdn.discordapp.com/emojis/1442619160751247440.png",
    "calendar": "https://cdn.discordapp.com/emojis/1442619163247120587.png",
    "battery_add": "https://cdn.discordapp.com/emojis/1442619164429914226.png",
    "battery_check": "https://cdn.discordapp.com/emojis/1442619165948121228.png",
    "battery_empty": "https://cdn.discordapp.com/emojis/1442619167193956382.png",
    "battery_high": "https://cdn.discordapp.com/emojis/1442619168666161162.png",
    "battery_low": "https://cdn.discordapp.com/emojis/1442619169920122913.png",
    "battery_medium": "https://cdn.discordapp.com/emojis/1442619178459730113.png",
    "battery_remove": "https://cdn.discordapp.com/emojis/1442619180724781188.png",
    "battery_x": "https://cdn.discordapp.com/emojis/1442619181534150779.png",
    "book_add": "https://cdn.discordapp.com/emojis/1442619183102824588.png",
    "book_check": "https://cdn.discordapp.com/emojis/1442619183983755316.png",
    "book_remove": "https://cdn.discordapp.com/emojis/1442619185996890142.png",
    "book_x": "https://cdn.discordapp.com/emojis/1442619187154522142.png",
    "book": "https://cdn.discordapp.com/emojis/1442619189037764619.png",
    "clipboard_add": "https://cdn.discordapp.com/emojis/1442619191902339142.png",
    "clipboard_check": "https://cdn.discordapp.com/emojis/1442619199561400361.png",
    "clipboard_clipboards": "https://cdn.discordapp.com/emojis/1442619200396071115.png",
    "clipboard_remove": "https://cdn.discordapp.com/emojis/1442619202388365442.png",
    "clipboard_x": "https://cdn.discordapp.com/emojis/1442619203734470878.png",
    "clipboard": "https://cdn.discordapp.com/emojis/1442619205093556295.png",
    "clock_add": "https://cdn.discordapp.com/emojis/1442619206464966849.png",
    "clock_check": "https://cdn.discordapp.com/emojis/1442619207966527589.png",
    "clock_remove": "https://cdn.discordapp.com/emojis/1442619209250111499.png",
    "clock_x": "https://cdn.discordapp.com/emojis/1442619210118467659.png",
    "clock": "https://cdn.discordapp.com/emojis/1442619211812835411.png",
    "cloud_add": "https://cdn.discordapp.com/emojis/1442619214266634291.png",
    "cloud_check": "https://cdn.discordapp.com/emojis/1442619216099278850.png",
    "cloud_remove": "https://cdn.discordapp.com/emojis/1442619218553077895.png",
    "cloud_x": "https://cdn.discordapp.com/emojis/1442619219605852384.png",
    "cloud": "https://cdn.discordapp.com/emojis/1442619220700565606.png",
    "database_add": "https://cdn.discordapp.com/emojis/1442619222059389098.png",
    "database_check": "https://cdn.discordapp.com/emojis/1442619223569600543.png",
    "database_remove": "https://cdn.discordapp.com/emojis/1442619224701931521.png",
    "database_x": "https://cdn.discordapp.com/emojis/1442619226375590003.png",
    "database": "https://cdn.discordapp.com/emojis/1442619228803825847.png",
    "dev_bun": "https://cdn.discordapp.com/emojis/1442619230791925935.png",
    "dev_javascript": "https://cdn.discordapp.com/emojis/1442619231974850782.png",
    "dev_nodejs": "https://cdn.discordapp.com/emojis/1442619233392525532.png",
    "dev_pnpm": "https://cdn.discordapp.com/emojis/1442619234667462686.png",
    "dev_typescript": "https://cdn.discordapp.com/emojis/1442619235519168656.png",
    "dev_yarn": "https://cdn.discordapp.com/emojis/1442619236701835429.png",
    "file_add": "https://cdn.discordapp.com/emojis/1442619238211784755.png",
    "file_check": "https://cdn.discordapp.com/emojis/1442619238899646666.png",
    "file_files": "https://cdn.discordapp.com/emojis/1442619240409731182.png",
    "file_remove": "https://cdn.discordapp.com/emojis/1442619241135079671.png",
    "file_x": "https://cdn.discordapp.com/emojis/1442619242582380601.png",
    "file": "https://cdn.discordapp.com/emojis/1442619243873964124.png",
    "device_desktop": "https://cdn.discordapp.com/emojis/1442619245455216722.png",
    "device_mobile": "https://cdn.discordapp.com/emojis/1442619246759772341.png",
    "device_tablet": "https://cdn.discordapp.com/emojis/1442619248819044404.png",
    "folder_add": "https://cdn.discordapp.com/emojis/1442619249817423934.png",
    "folder_open": "https://cdn.discordapp.com/emojis/1442619251499470949.png",
    "folder_remove": "https://cdn.discordapp.com/emojis/1442619252577140977.png",
    "folder": "https://cdn.discordapp.com/emojis/1442619253403680800.png",
    "location_add": "https://cdn.discordapp.com/emojis/1442619256054223080.png",
    "location_check": "https://cdn.discordapp.com/emojis/1442619257744527561.png",
    "location_off": "https://cdn.discordapp.com/emojis/1442619259590152244.png",
    "location_remove": "https://cdn.discordapp.com/emojis/1442619260802437245.png",
    "location_x": "https://cdn.discordapp.com/emojis/1442619263272882320.png",
    "location": "https://cdn.discordapp.com/emojis/1442619264920977491.png",
    "lock_add": "https://cdn.discordapp.com/emojis/1442619268431609976.png",
    "lock_check": "https://cdn.discordapp.com/emojis/1442619269379653643.png",
    "lock_remove": "https://cdn.discordapp.com/emojis/1442619270747132027.png",
    "lock_x": "https://cdn.discordapp.com/emojis/1442619278200274995.png",
    "lock": "https://cdn.discordapp.com/emojis/1442619279781527725.png",
    "mail_add": "https://cdn.discordapp.com/emojis/1442619282411229306.png",
    "mail_check": "https://cdn.discordapp.com/emojis/1442619283594018937.png",
    "mail_mails": "https://cdn.discordapp.com/emojis/1442619284843925716.png",
    "mail_remove": "https://cdn.discordapp.com/emojis/1442619286093955153.png",
    "mail_x": "https://cdn.discordapp.com/emojis/1442619287402451017.png",
    "mail": "https://cdn.discordapp.com/emojis/1442619288669130922.png",
    "number_eight": "https://cdn.discordapp.com/emojis/1442619289956909159.png",
    "number_five": "https://cdn.discordapp.com/emojis/1442619291303415919.png",
    "number_four": "https://cdn.discordapp.com/emojis/1442619292133621932.png",
    "number_nine": "https://cdn.discordapp.com/emojis/1442619293987508265.png",
    "number_one": "https://cdn.discordapp.com/emojis/1442619295312908529.png",
    "number_seven": "https://cdn.discordapp.com/emojis/1442619297770897428.png",
    "number_six": "https://cdn.discordapp.com/emojis/1442619299406676058.png",
    "number_three": "https://cdn.discordapp.com/emojis/1442619300501262428.png",
    "number_two": "https://cdn.discordapp.com/emojis/1442619302250287114.png",
    "number_zero": "https://cdn.discordapp.com/emojis/1442619303441727628.png",
    "search_add": "https://cdn.discordapp.com/emojis/1442619304632778984.png",
    "search_check": "https://cdn.discordapp.com/emojis/1442619305727361065.png",
    "search_remove": "https://cdn.discordapp.com/emojis/1442619306952097964.png",
    "search_x": "https://cdn.discordapp.com/emojis/1442619308378165401.png",
    "search": "https://cdn.discordapp.com/emojis/1442619310198624440.png",
    "other_academycap": "https://cdn.discordapp.com/emojis/1442619311481946243.png",
    "other_bank": "https://cdn.discordapp.com/emojis/1442619312975249408.png",
    "other_bot": "https://cdn.discordapp.com/emojis/1442619314133008485.png",
    "other_brain": "https://cdn.discordapp.com/emojis/1442619315563266239.png",
    "other_bug": "https://cdn.discordapp.com/emojis/1442619316779483167.png",
    "other_card": "https://cdn.discordapp.com/emojis/1442619317920338082.png",
    "other_dollar": "https://cdn.discordapp.com/emojis/1442619319363305703.png",
    "other_home": "https://cdn.discordapp.com/emojis/1442619320386457751.png",
    "other_key": "https://cdn.discordapp.com/emojis/1442619321753796740.png",
    "other_megaphone": "https://cdn.discordapp.com/emojis/1442619323515404299.png",
    "other_save": "https://cdn.discordapp.com/emojis/1442619326979903553.png",
    "other_terminal": "https://cdn.discordapp.com/emojis/1442619330436137033.png",
    "other_ticket": "https://cdn.discordapp.com/emojis/1442619333993041920.png",
    "other_wallet": "https://cdn.discordapp.com/emojis/1442619336064766135.png",
    "shield_add": "https://cdn.discordapp.com/emojis/1442619337662791680.png",
    "shield_check": "https://cdn.discordapp.com/emojis/1442619338862366740.png",
    "shield_remove": "https://cdn.discordapp.com/emojis/1442619340649271377.png",
    "shield_x": "https://cdn.discordapp.com/emojis/1442619343245541388.png",
    "shield": "https://cdn.discordapp.com/emojis/1442619344210362480.png",
    "unlock_add": "https://cdn.discordapp.com/emojis/1442619345992941851.png",
    "unlock_check": "https://cdn.discordapp.com/emojis/1442619347351769090.png",
    "unlock_remove": "https://cdn.discordapp.com/emojis/1442619348949667860.png",
    "unlock_x": "https://cdn.discordapp.com/emojis/1442619350560280596.png",
    "unlock": "https://cdn.discordapp.com/emojis/1442619351969697883.png",
    "user_add": "https://cdn.discordapp.com/emojis/1442619353387499590.png",
    "user_check": "https://cdn.discordapp.com/emojis/1442619356319322182.png",
    "user_remove": "https://cdn.discordapp.com/emojis/1442619360358301796.png",
    "user_users": "https://cdn.discordapp.com/emojis/1442619361499025579.png",
    "user_x": "https://cdn.discordapp.com/emojis/1442619362753380452.png",
    "user": "https://cdn.discordapp.com/emojis/1442619364271591585.png",
    "dec": "https://cdn.discordapp.com/emojis/1445049460655919175.png",
    "dl": "https://cdn.discordapp.com/emojis/1445049468226633868.png",
    "dp": "https://cdn.discordapp.com/emojis/1445049469652566116.png",
    "dtic": "https://cdn.discordapp.com/emojis/1445049471195943075.png",
    "pmesp": "https://cdn.discordapp.com/emojis/1445051035101040831.png",
    "correg": "https://cdn.discordapp.com/emojis/1446299024457072754.png",
    "ctg1": "https://cdn.discordapp.com/emojis/1446299519968084133.png",
    "empm": "https://cdn.discordapp.com/emojis/1446300397990838395.png"
  },
  "animated": {}
}